password_sandbox/__about__.py
password_sandbox/__init__.py
password_sandbox-1.0.0.dist-info/METADATA
password_sandbox-1.0.0.dist-info/WHEEL
password_sandbox-1.0.0.dist-info/licenses/LICENSE.txt
password_sandbox-1.0.0.dist-info/RECORD
