Metadata-Version: 2.1
Name: password-sandbox
Version: 1.0.0
Summary: Password Sandbox is password sandbox to create strong passwords and test the strength of your passwords.
Project-URL: Documentation, https://github.com/Useless-Projects/password-sandbox#readme
Project-URL: Issues, https://github.com/Useless-Projects/password-sandbox/issues
Project-URL: Source, https://github.com/Useless-Projects/password-sandbox
Author-email: Thibault Savenkoff <thibault.savenkoff@outlook.fr>
License-Expression: MIT
License-File: LICENSE.txt
Classifier: Development Status :: 4 - Beta
Classifier: Programming Language :: Python
Classifier: Programming Language :: Python :: 3.7
Classifier: Programming Language :: Python :: 3.8
Classifier: Programming Language :: Python :: 3.9
Classifier: Programming Language :: Python :: 3.10
Classifier: Programming Language :: Python :: 3.11
Classifier: Programming Language :: Python :: 3.12
Classifier: Programming Language :: Python :: Implementation :: CPython
Classifier: Programming Language :: Python :: Implementation :: PyPy
Requires-Python: >=3.7
Requires-Dist: zxcvbn
